spiralpy/CMakeLists.txt
spiralpy/__init__.py
spiralpy/batchmddftsolver.py
spiralpy/constants.py
spiralpy/dftsolver.py
spiralpy/hockneysolver.py
spiralpy/mddftsolver.py
spiralpy/mdprdftsolver.py
spiralpy/mdrconvsolver.py
spiralpy/mdrfsconvsolver.py
spiralpy/metadata.py
spiralpy/spiral.py
spiralpy/spsolver.py
spiralpy/stepphasesolver.py
spiralpy-1.0.4.data/data/share/spiralpy/Contributing.md
spiralpy-1.0.4.data/data/share/spiralpy/README.md
spiralpy-1.0.4.data/data/share/spiralpy/examples/print-metadata.py
spiralpy-1.0.4.data/data/share/spiralpy/examples/run-batchdft.py
spiralpy-1.0.4.data/data/share/spiralpy/examples/run-batchmddft.py
spiralpy-1.0.4.data/data/share/spiralpy/examples/run-dft.py
spiralpy-1.0.4.data/data/share/spiralpy/examples/run-hockney130.py
spiralpy-1.0.4.data/data/share/spiralpy/examples/run-hockney8.py
spiralpy-1.0.4.data/data/share/spiralpy/examples/run-mddft.py
spiralpy-1.0.4.data/data/share/spiralpy/examples/run-mdprdft.py
spiralpy-1.0.4.data/data/share/spiralpy/examples/run-mdrconv.py
spiralpy-1.0.4.data/data/share/spiralpy/examples/run-mdrfsconv.py
spiralpy-1.0.4.data/data/share/spiralpy/examples/run-stepphase.py
spiralpy-1.0.4.data/data/share/spiralpy/examples/test-many.sh
spiralpy-1.0.4.dist-info/LICENSE
spiralpy-1.0.4.dist-info/METADATA
spiralpy-1.0.4.dist-info/WHEEL
spiralpy-1.0.4.dist-info/top_level.txt
spiralpy-1.0.4.dist-info/RECORD
